dotnote/__init__.py
DotNote-1.1.8.dist-info/LICENSE
DotNote-1.1.8.dist-info/METADATA
DotNote-1.1.8.dist-info/WHEEL
DotNote-1.1.8.dist-info/top_level.txt
DotNote-1.1.8.dist-info/RECORD
