Metadata-Version: 2.1
Name: DotNote
Version: 1.1.8
Summary: Reading and Parsing note files
Home-page: https://www.beyonce.com/
Author: hunterg
Author-email: redissuslolol@gmail.com
License: UNKNOWN
Platform: UNKNOWN
Classifier: Programming Language :: Python :: 3
Classifier: License :: OSI Approved :: MIT License
Classifier: Operating System :: OS Independent
Requires-Python: >=3.6
Requires-Dist: getFN
